binance_sdk_derivatives_trading_coin_futures/__init__.py
binance_sdk_derivatives_trading_coin_futures/derivatives_trading_coin_futures.py
binance_sdk_derivatives_trading_coin_futures/metadata.py
binance_sdk_derivatives_trading_coin_futures/rest_api/__init__.py
binance_sdk_derivatives_trading_coin_futures/rest_api/api/__init__.py
binance_sdk_derivatives_trading_coin_futures/rest_api/api/account_api.py
binance_sdk_derivatives_trading_coin_futures/rest_api/api/market_data_api.py
binance_sdk_derivatives_trading_coin_futures/rest_api/api/portfolio_margin_endpoints_api.py
binance_sdk_derivatives_trading_coin_futures/rest_api/api/trade_api.py
binance_sdk_derivatives_trading_coin_futures/rest_api/api/user_data_streams_api.py
binance_sdk_derivatives_trading_coin_futures/rest_api/models/__init__.py
binance_sdk_derivatives_trading_coin_futures/rest_api/models/account_information_response.py
binance_sdk_derivatives_trading_coin_futures/rest_api/models/account_information_response_assets_inner.py
binance_sdk_derivatives_trading_coin_futures/rest_api/models/account_information_response_positions_inner.py
binance_sdk_derivatives_trading_coin_futures/rest_api/models/account_trade_list_response.py
binance_sdk_derivatives_trading_coin_futures/rest_api/models/account_trade_list_response_inner.py
binance_sdk_derivatives_trading_coin_futures/rest_api/models/all_orders_response.py
binance_sdk_derivatives_trading_coin_futures/rest_api/models/all_orders_response_inner.py
binance_sdk_derivatives_trading_coin_futures/rest_api/models/auto_cancel_all_open_orders_response.py
binance_sdk_derivatives_trading_coin_futures/rest_api/models/basis_response.py
binance_sdk_derivatives_trading_coin_futures/rest_api/models/basis_response_inner.py
binance_sdk_derivatives_trading_coin_futures/rest_api/models/cancel_all_open_orders_response.py
binance_sdk_derivatives_trading_coin_futures/rest_api/models/cancel_multiple_orders_response.py
binance_sdk_derivatives_trading_coin_futures-3.3.0.dist-info/METADATA
binance_sdk_derivatives_trading_coin_futures-3.3.0.dist-info/WHEEL
binance_sdk_derivatives_trading_coin_futures-3.3.0.dist-info/licenses/LICENCE
binance_sdk_derivatives_trading_coin_futures-3.3.0.dist-info/RECORD
